Workbook

Sheet Menu
B2: Organizador do Imposto de Renda
B3: Reúna rendimentos, despesas, bens e dívidas em um só lugar e confira o resumo antes de declarar.
B5: 1. Parâmetros | C5: Ano-calendário e valores de referência (limites e deduções).
B6: 2. Dependentes | C6: Cadastre dependentes e veja a idade automaticamente.
B7: 3. Rendimentos | C7: Salários, aluguéis, dividendos e outras entradas, com IRRF.
B8: 4. Despesas dedutíveis | C8: Saúde, educação, PGBL, pensão alimentícia e livro-caixa.
B9: 5. Bens e direitos | C9: Imóveis, veículos, contas e investimentos.
B10: 6. Dívidas e ônus | C10: Financiamentos e empréstimos.
B11: 7. Resumo | C11: Totais, comparativo de modelos, patrimônio e pendências.
B12: 8. Links rápidos | C12: Sites oficiais da Receita Federal e serviços úteis.
B13: 9. Listas (menus suspensos) | C13: Edite as opções usadas nos menus de seleção.
B15: Como usar
B16: • Preencha as células em branco a partir da linha 6 de cada aba; a linha amarela (linha 5) é apenas um exemplo.
B17: • Campos com menu suspenso só aceitam opções da lista; datas, valores e CPF/CNPJ são validados automaticamente.
B18: • Células cinzas são fórmulas — não digite nelas.
B19: • Células vermelhas em CPF/CNPJ indicam valor lançado sem documento da fonte/prestador.
B20: • Confira os parâmetros do ano na aba Parametros. O Resumo é apenas apoio: o cálculo oficial é do programa da Receita.

Sheet Parametros
A1: Parâmetros do ano
A2: Células amarelas são editáveis. CONFIRA os valores na tabela oficial da Receita Federal do ano.
A3: ← Voltar ao Menu
A5: Ano-calendário | B5: 2025 | C5: Ano dos rendimentos que serão declarados.
A6: Dedução anual por dependente (R$) | B6: 2275.08 | C6: Valor de referência (2025). Confirme no site da Receita.
A7: Limite anual de dedução com instrução, por pessoa (R$) | B7: 3561.5 | C7: Valor de referência (2025). Confirme no site da Receita.
A8: Limite de dedução da previdência privada (PGBL) | B8: 0.12 | C8: % dos rendimentos tributáveis.
A9: Desconto simplificado — percentual | B9: 0.2 | C9: Valor de referência. Confirme no site da Receita.
A10: Desconto simplificado — limite (R$) | B10: 16754.34 | C10: Valor de referência. Confirme no site da Receita.

Sheet Dependentes
A1: Dependentes
A2: Cadastre os dependentes antes de lançar despesas. Linha amarela = exemplo (fora dos cálculos).
A3: ← Voltar ao Menu
A4: Nome | B4: CPF | C4: Data de nascimento | D4: Parentesco | E4: Dependente ativo? | F4: Idade (anos)
A5: Maria Silva (exemplo) | B5: 123.456.789-09 | C5: 42075 | D5: Filho(a) até 21 anos | E5: Sim | F5: =DATEDIF(C5,TODAY(),"Y") -> 11
F6: =IF(C6="","",DATEDIF(C6,TODAY(),"Y"))
F7: =IF(C7="","",DATEDIF(C7,TODAY(),"Y"))
F8: =IF(C8="","",DATEDIF(C8,TODAY(),"Y"))
F9: =IF(C9="","",DATEDIF(C9,TODAY(),"Y"))
F10: =IF(C10="","",DATEDIF(C10,TODAY(),"Y"))
F11: =IF(C11="","",DATEDIF(C11,TODAY(),"Y"))
F12: =IF(C12="","",DATEDIF(C12,TODAY(),"Y"))
F13: =IF(C13="","",DATEDIF(C13,TODAY(),"Y"))
F14: =IF(C14="","",DATEDIF(C14,TODAY(),"Y"))
F15: =IF(C15="","",DATEDIF(C15,TODAY(),"Y"))
F16: =IF(C16="","",DATEDIF(C16,TODAY(),"Y"))
F17: =IF(C17="","",DATEDIF(C17,TODAY(),"Y"))
... F35: =IF(C35="","",DATEDIF(C35,TODAY(),"Y"))

Sheet Rendimentos
A1: Rendimentos recebidos
A2: Lance cada fonte pagadora. A coluna Classificação é preenchida automaticamente. Linha amarela = exemplo.
A3: ← Voltar ao Menu
A4: Data | B4: Tipo de rendimento | C4: Fonte pagadora | D4: CPF/CNPJ da fonte | E4: Titular / Dependente | F4: Valor bruto (R$) | G4: IRRF retido (R$) | H4: Previdência oficial (R$) | I4: Observações | J4: Classificação
A5: 45996 | B5: Salário / pró-labore | C5: Empresa Exemplo Ltda | D5: 12.345.678/0001-95 | E5: Titular | F5: 5000 | G5: 450 | H5: 550 | I5: Exemplo — apague ou sobrescreva | J5: Tributável
J6: =IF(B6="","",IFERROR(INDEX(Listas!$B$2:$B$40,MATCH(B6,Listas!$A$2:$A$40,0)),""))
J7: =IF(B7="","",IFERROR(INDEX(Listas!$B$2:$B$40,MATCH(B7,Listas!$A$2:$A$40,0)),""))
J8: =IF(B8="","",IFERROR(INDEX(Listas!$B$2:$B$40,MATCH(B8,Listas!$A$2:$A$40,0)),""))
J9: =IF(B9="","",IFERROR(INDEX(Listas!$B$2:$B$40,MATCH(B9,Listas!$A$2:$A$40,0)),""))
J10: =IF(B10="","",IFERROR(INDEX(Listas!$B$2:$B$40,MATCH(B10,Listas!$A$2:$A$40,0)),""))
J11: =IF(B11="","",IFERROR(INDEX(Listas!$B$2:$B$40,MATCH(B11,Listas!$A$2:$A$40,0)),""))
J12: =IF(B12="","",IFERROR(INDEX(Listas!$B$2:$B$40,MATCH(B12,Listas!$A$2:$A$40,0)),""))
J13: =IF(B13="","",IFERROR(INDEX(Listas!$B$2:$B$40,MATCH(B13,Listas!$A$2:$A$40,0)),""))
J14: =IF(B14="","",IFERROR(INDEX(Listas!$B$2:$B$40,MATCH(B14,Listas!$A$2:$A$40,0)),""))
J15: =IF(B15="","",IFERROR(INDEX(Listas!$B$2:$B$40,MATCH(B15,Listas!$A$2:$A$40,0)),""))
J16: =IF(B16="","",IFERROR(INDEX(Listas!$B$2:$B$40,MATCH(B16,Listas!$A$2:$A$40,0)),""))
J17: =IF(B17="","",IFERROR(INDEX(Listas!$B$2:$B$40,MATCH(B17,Listas!$A$2:$A$40,0)),""))
... J505: =IF(B505="","",IFERROR(INDEX(Listas!$B$2:$B$40,MATCH(B505,Listas!$A$2:$A$40,0)),""))

Sheet Deducoes
A1: Despesas dedutíveis
A2: Saúde, educação, previdência privada, pensão e livro-caixa. Linha amarela = exemplo.
A3: ← Voltar ao Menu
A4: Data | B4: Tipo de dedução | C4: Beneficiário | D4: Prestador / Profissional | E4: CPF/CNPJ do prestador | F4: Valor pago (R$) | G4: Reembolsado (R$) | H4: Valor líquido (R$) | I4: Comprovante / Observações
A5: 45826 | B5: Saúde | C5: Titular | D5: Clínica Exemplo S/S | E5: 98.765.432/0001-10 | F5: 800 | G5: 0 | H5: 800 | I5: Recibo nº 123 (exemplo)
H6: =IF(F6="","",MAX(0,F6-N(G6)))
H7: =IF(F7="","",MAX(0,F7-N(G7)))
H8: =IF(F8="","",MAX(0,F8-N(G8)))
H9: =IF(F9="","",MAX(0,F9-N(G9)))
H10: =IF(F10="","",MAX(0,F10-N(G10)))
H11: =IF(F11="","",MAX(0,F11-N(G11)))
H12: =IF(F12="","",MAX(0,F12-N(G12)))
H13: =IF(F13="","",MAX(0,F13-N(G13)))
H14: =IF(F14="","",MAX(0,F14-N(G14)))
H15: =IF(F15="","",MAX(0,F15-N(G15)))
H16: =IF(F16="","",MAX(0,F16-N(G16)))
H17: =IF(F17="","",MAX(0,F17-N(G17)))
... H505: =IF(F505="","",MAX(0,F505-N(G505)))

Sheet Bens_Direitos
A1: Bens e direitos
A2: Informe a situação em 31/12 do ano anterior e do ano-calendário. Linha amarela = exemplo.
A3: ← Voltar ao Menu
A4: Grupo | B4: Discriminação | C4: Data de aquisição | D4: CPF/CNPJ (banco, corretora, etc.) | E4: Situação em 31/12 ano anterior (R$) | F4: Situação em 31/12 ano atual (R$) | G4: Observações
A5: 06 - Depósitos à vista / contas | B5: Conta corrente — Banco Exemplo, ag. 0001 | C5: 43110 | D5: 00.000.000/0001-91 | E5: 3200 | F5: 4100 | G5: Exemplo

Sheet Dividas
A1: Dívidas e ônus reais
A2: Financiamentos, empréstimos e outras dívidas. Linha amarela = exemplo.
A3: ← Voltar ao Menu
A4: Credor | B4: CPF/CNPJ do credor | C4: Descrição | D4: Saldo em 31/12 ano anterior (R$) | E4: Saldo em 31/12 ano atual (R$) | F4: Observações
A5: Banco Exemplo S.A. | B5: 00.000.000/0001-91 | C5: Financiamento de veículo | D5: 18000 | E5: 12000 | F5: Exemplo

Sheet Resumo
A1: Resumo para a declaração
A2: Tudo é calculado automaticamente a partir das abas de lançamento.
A3: ← Voltar ao Menu
A5: RENDIMENTOS
A6: Rendimentos tributáveis | B6: =SUMIFS(Rendimentos!$F$6:$F$505,Rendimentos!$J$6:$J$505,"Tributável") -> 0
A7: Rendimentos sujeitos à tributação exclusiva | B7: =SUMIFS(Rendimentos!$F$6:$F$505,Rendimentos!$J$6:$J$505,"Exclusivo na fonte") -> 0
A8: Rendimentos isentos e não tributáveis | B8: =SUMIFS(Rendimentos!$F$6:$F$505,Rendimentos!$J$6:$J$505,"Isento") -> 0
A9: Imposto retido na fonte (IRRF) | B9: =SUM(Rendimentos!$G$6:$G$505) -> 0
A10: DEDUÇÕES (modelo completo)
A11: Contribuição previdenciária oficial | B11: =SUM(Rendimentos!$H$6:$H$505) -> 0
A12: Despesas com saúde (líquidas de reembolso) | B12: =SUMIFS(Deducoes!$H$6:$H$505,Deducoes!$B$6:$B$505,"Saúde") -> 0 | C12: Sem limite de valor.
A13: Despesas com educação informadas | B13: =SUMIFS(Deducoes!$H$6:$H$505,Deducoes!$B$6:$B$505,"Educação") -> 0
A14: Quantidade de dependentes ativos | B14: =COUNTIFS(Dependentes!$A$6:$A$35,"<>",Dependentes!$E$6:$E$35,"Sim") -> 0
A15: Educação dedutível (estimativa) | B15: =MIN(B13,Parametros!B7*(1+B14)) -> 0 | C15: Limite por pessoa × (titular + dependentes). Estimativa: o limite real vale por pessoa.
A16: Dedução com dependentes | B16: =B14*Parametros!B6 -> 0
A17: Previdência privada (PGBL) dedutível | B17: =MIN(SUMIFS(Deducoes!$H$6:$H$505,Deducoes!$B$6:$B$505,"Previdência privada (PGBL)"),Parametros!B8*B6) -> 0 | C17: Limitada a % dos rendimentos tributáveis.
A18: Pensão alimentícia | B18: =SUMIFS(Deducoes!$H$6:$H$505,Deducoes!$B$6:$B$505,"Pensão alimentícia") -> 0
A19: Livro-caixa | B19: =SUMIFS(Deducoes!$H$6:$H$505,Deducoes!$B$6:$B$505,"Livro-caixa") -> 0
A20: Total de deduções legais | B20: =B11+B12+B15+B16+B17+B18+B19 -> 0
A21: COMPARATIVO DE MODELOS (estimativa de base de cálculo)
A22: Base de cálculo — modelo completo | B22: =MAX(0,B6-B20) -> 0 | C22: Rendimentos tributáveis − deduções legais.
A23: Desconto simplificado | B23: =MIN(B6*Parametros!B9,Parametros!B10) -> 0 | C23: Confira os parâmetros na aba Parametros.
A24: Base de cálculo — modelo simplificado | B24: =MAX(0,B6-B23) -> 0
A25: Modelo com menor base de cálculo | B25: =IF(B22<=B24,"Completo","Simplificado") -> Completo | C25: Indicativo. O programa da Receita faz o cálculo oficial.
A26: PATRIMÔNIO
A27: Bens e direitos — 31/12 ano anterior | B27: =SUM(Bens_Direitos!$E$6:$E$505) -> 0
A28: Bens e direitos — 31/12 ano atual | B28: =SUM(Bens_Direitos!$F$6:$F$505) -> 0
A29: Dívidas — 31/12 ano anterior | B29: =SUM(Dividas!$D$6:$D$505) -> 0
A30: Dívidas — 31/12 ano atual | B30: =SUM(Dividas!$E$6:$E$505) -> 0
A31: Patrimônio líquido — ano anterior | B31: =B27-B29 -> 0
A32: Patrimônio líquido — ano atual | B32: =B28-B30 -> 0
A33: Variação patrimonial | B33: =B32-B31 -> 0
A34: PENDÊNCIAS
A35: Rendimentos sem CPF/CNPJ da fonte | B35: =SUMPRODUCT((Rendimentos!$F$6:$F$505<>"")*(Rendimentos!$D$6:$D$505="")) -> 0 | C35: Deve ser zero antes de declarar.
A36: Despesas dedutíveis sem CPF/CNPJ do prestador | B36: =SUMPRODUCT((Deducoes!$F$6:$F$505<>"")*(Deducoes!$E$6:$E$505="")) -> 0 | C36: Deve ser zero antes de declarar.
A37: Situação | B37: =IF(B35+B36=0,"Tudo certo ✔","Há pendências ✖") -> Tudo certo ✔

Sheet Links
A1: Links rápidos
A2: Sites oficiais úteis durante a declaração (abrem no navegador).
A3: ← Voltar ao Menu
A5: Serviço | B5: Endereço / descrição
A6: Meu Imposto de Renda (Receita Federal) | B6: Programa, prazos, perguntas e respostas.
A7: Portal e-CAC | B7: Declaração pré-preenchida, extratos e situação fiscal.
A8: Consulta à restituição | B8: Acompanhe a restituição do imposto.
A9: Consulta de CNPJ | B9: Confirme o CNPJ de fontes e prestadores.
A10: Meu INSS | B10: Informe de rendimentos de aposentadoria e pensão.
A11: Gov.br | B11: Acesso aos serviços digitais do governo.

Sheet Listas
A1: Tipo de rendimento | B1: Classificação | D1: Tipo de dedução | F1: Beneficiário | H1: Parentesco | J1: Sim/Não | L1: Grupo do bem
A2: Salário / pró-labore | B2: Tributável | D2: Saúde | F2: Titular | H2: Cônjuge / companheiro(a) | J2: Sim | L2: 01 - Imóveis
A3: Aposentadoria / pensão (tributável) | B3: Tributável | D3: Educação | F3: =IF(Dependentes!A6="","",Dependentes!A6) | H3: Filho(a) até 21 anos | J3: Não | L3: 02 - Veículos
A4: Aluguel recebido | B4: Tributável | D4: Previdência privada (PGBL) | F4: =IF(Dependentes!A7="","",Dependentes!A7) | H4: Filho(a) até 24 anos (universitário) | L4: 03 - Participações societárias
A5: Trabalho autônomo | B5: Tributável | D5: Pensão alimentícia | F5: =IF(Dependentes!A8="","",Dependentes!A8) | H5: Filho(a) incapaz | L5: 04 - Aplicações e investimentos
A6: Rendimento recebido de pessoa física | B6: Tributável | D6: Livro-caixa | F6: =IF(Dependentes!A9="","",Dependentes!A9) | H6: Pais / avós | L6: 06 - Depósitos à vista / contas
A7: 13º salário | B7: Exclusivo na fonte | F7: =IF(Dependentes!A10="","",Dependentes!A10) | H7: Menor sob guarda | L7: 07 - Fundos
A8: PLR | B8: Exclusivo na fonte | F8: =IF(Dependentes!A11="","",Dependentes!A11) | H8: Outro | L8: 08 - Criptoativos
A9: Rendimento de aplicação financeira | B9: Exclusivo na fonte | F9: =IF(Dependentes!A12="","",Dependentes!A12) | L9: 99 - Outros bens e direitos
A10: Juros sobre capital próprio | B10: Exclusivo na fonte | F10: =IF(Dependentes!A13="","",Dependentes!A13)
A11: Lucros e dividendos | B11: Isento | F11: =IF(Dependentes!A14="","",Dependentes!A14)
A12: Poupança / LCI / LCA | B12: Isento | F12: =IF(Dependentes!A15="","",Dependentes!A15)
A13: Indenização / FGTS | B13: Isento | F13: =IF(Dependentes!A16="","",Dependentes!A16)
A14: Herança / doação recebida | B14: Isento | F14: =IF(Dependentes!A17="","",Dependentes!A17)
A15: Outros rendimentos isentos | B15: Isento | F15: =IF(Dependentes!A18="","",Dependentes!A18)
F16: =IF(Dependentes!A19="","",Dependentes!A19)
F17: =IF(Dependentes!A20="","",Dependentes!A20)
A18: Edite estas listas para ajustar as opções dos menus suspensos. A classificação (coluna B) alimenta o Resumo. | F18: =IF(Dependentes!A21="","",Dependentes!A21)
F19: =IF(Dependentes!A22="","",Dependentes!A22)
F20: =IF(Dependentes!A23="","",Dependentes!A23)
F21: =IF(Dependentes!A24="","",Dependentes!A24)
F22: =IF(Dependentes!A25="","",Dependentes!A25)
F23: =IF(Dependentes!A26="","",Dependentes!A26)
F24: =IF(Dependentes!A27="","",Dependentes!A27)
F25: =IF(Dependentes!A28="","",Dependentes!A28)
F26: =IF(Dependentes!A29="","",Dependentes!A29)
F27: =IF(Dependentes!A30="","",Dependentes!A30)
F28: =IF(Dependentes!A31="","",Dependentes!A31)
F29: =IF(Dependentes!A32="","",Dependentes!A32)
F30: =IF(Dependentes!A33="","",Dependentes!A33)
... F32: =IF(Dependentes!A35="","",Dependentes!A35)
